{
  "champions": [
    {
      "image": "https://opgg-static.akamaized.net/meta/images/lol/15.19.1/champion/Neeko.png?image=c_crop,h_103,w_103,x_9,y_9/q_auto:good,f_png,w_160,h_160&v=1519",
      "name": "万花通灵",
      "id": 1
    },
    {
      "image": "https://opgg-static.akamaized.net/meta/images/lol/15.19.1/champion/Skarner.png?image=c_crop,h_103,w_103,x_9,y_9/q_auto:good,f_png,w_160,h_160&v=1519",
      "name": "上古领主",
      "id": 2
    },
    {
      "image": "https://opgg-static.akamaized.net/meta/images/lol/15.19.1/champion/Pantheon.png?image=c_crop,h_103,w_103,x_9,y_9/q_auto:good,f_png,w_160,h_160&v=1519",
      "name": "不屈之枪",
      "id": 3
    },
    {
      "image": "https://opgg-static.akamaized.net/meta/images/lol/15.19.1/champion/Volibear.png?image=c_crop,h_103,w_103,x_9,y_9/q_auto:good,f_png,w_160,h_160&v=1519",
      "name": "不灭狂雷",
      "id": 4
    },
    {
      "image": "https://opgg-static.akamaized.net/meta/images/lol/15.19.1/champion/Yunara.png?image=c_crop,h_103,w_103,x_9,y_9/q_auto:good,f_png,w_160,h_160&v=1519",
      "name": "不破之誓",
      "id": 5
    },
    {
      "image": "https://opgg-static.akamaized.net/meta/images/lol/15.19.1/champion/Katarina.png?image=c_crop,h_103,w_103,x_9,y_9/q_auto:good,f_png,w_160,h_160&v=1519",
      "name": "不祥之刃",
      "id": 6
    },
    {
      "image": "https://opgg-static.akamaized.net/meta/images/lol/15.19.1/champion/Nilah.png?image=c_crop,h_103,w_103,x_9,y_9/q_auto:good,f_png,w_160,h_160&v=1519",
      "name": "不羁之悦",
      "id": 7
    },
    {
      "image": "https://opgg-static.akamaized.net/meta/images/lol/15.19.1/champion/Ahri.png?image=c_crop,h_103,w_103,x_9,y_9/q_auto:good,f_png,w_160,h_160&v=1519",
      "name": "九尾妖狐",
      "id": 8
    },
    {
      "image": "https://opgg-static.akamaized.net/meta/images/lol/15.19.1/champion/Sion.png?image=c_crop,h_103,w_103,x_9,y_9/q_auto:good,f_png,w_160,h_160&v=1519",
      "name": "亡灵战神",
      "id": 9
    },
    {
      "image": "https://opgg-static.akamaized.net/meta/images/lol/15.19.1/champion/Lulu.png?image=c_crop,h_103,w_103,x_9,y_9/q_auto:good,f_png,w_160,h_160&v=1519",
      "name": "仙灵女巫",
      "id": 10
    },
    {
      "image": "https://opgg-static.akamaized.net/meta/images/lol/15.19.1/champion/Soraka.png?image=c_crop,h_103,w_103,x_9,y_9/q_auto:good,f_png,w_160,h_160&v=1519",
      "name": "众星之子",
      "id": 11
    },
    {
      "image": "https://opgg-static.akamaized.net/meta/images/lol/15.19.1/champion/Rengar.png?image=c_crop,h_103,w_103,x_9,y_9/q_auto:good,f_png,w_160,h_160&v=1519",
      "name": "傲之追猎者",
      "id": 12
    },
    {
      "image": "https://opgg-static.akamaized.net/meta/images/lol/15.19.1/champion/Qiyana.png?image=c_crop,h_103,w_103,x_9,y_9/q_auto:good,f_png,w_160,h_160&v=1519",
      "name": "元素女皇",
      "id": 13
    },
    {
      "image": "https://opgg-static.akamaized.net/meta/images/lol/15.19.1/champion/Lux.png?image=c_crop,h_103,w_103,x_9,y_9/q_auto:good,f_png,w_160,h_160&v=1519",
      "name": "光辉女郎",
      "id": 14
    },
    {
      "image": "https://opgg-static.akamaized.net/meta/images/lol/15.19.1/champion/Udyr.png?image=c_crop,h_103,w_103,x_9,y_9/q_auto:good,f_png,w_160,h_160&v=1519",
      "name": "兽灵行者",
      "id": 15
    },
    {
      "image": "https://opgg-static.akamaized.net/meta/images/lol/15.19.1/champion/Anivia.png?image=c_crop,h_103,w_103,x_9,y_9/q_auto:good,f_png,w_160,h_160&v=1519",
      "name": "冰晶凤凰",
      "id": 16
    },
    {
      "image": "https://opgg-static.akamaized.net/meta/images/lol/15.19.1/champion/Lissandra.png?image=c_crop,h_103,w_103,x_9,y_9/q_auto:good,f_png,w_160,h_160&v=1519",
      "name": "冰霜女巫",
      "id": 17
    },
    {
      "image": "https://opgg-static.akamaized.net/meta/images/lol/15.19.1/champion/Talon.png?image=c_crop,h_103,w_103,x_9,y_9/q_auto:good,f_png,w_160,h_160&v=1519",
      "name": "刀锋之影",
      "id": 18
    },
    {
      "image": "https://opgg-static.akamaized.net/meta/images/lol/15.19.1/champion/Irelia.png?image=c_crop,h_103,w_103,x_9,y_9/q_auto:good,f_png,w_160,h_160&v=1519",
      "name": "刀锋舞者",
      "id": 19
    },
    {
      "image": "https://opgg-static.akamaized.net/meta/images/lol/15.19.1/champion/Sejuani.png?image=c_crop,h_103,w_103,x_9,y_9/q_auto:good,f_png,w_160,h_160&v=1519",
      "name": "北地之怒",
      "id": 20
    },
    {
      "image": "https://opgg-static.akamaized.net/meta/images/lol/15.19.1/champion/TwistedFate.png?image=c_crop,h_103,w_103,x_9,y_9/q_auto:good,f_png,w_160,h_160&v=1519",
      "name": "卡牌大师",
      "id": 21
    },
    {
      "image": "https://opgg-static.akamaized.net/meta/images/lol/15.19.1/champion/Aurora.png?image=c_crop,h_103,w_103,x_9,y_9/q_auto:good,f_png,w_160,h_160&v=1519",
      "name": "双界灵兔",
      "id": 22
    },
    {
      "image": "https://opgg-static.akamaized.net/meta/images/lol/15.19.1/champion/Orianna.png?image=c_crop,h_103,w_103,x_9,y_9/q_auto:good,f_png,w_160,h_160&v=1519",
      "name": "发条魔灵",
      "id": 23
    },
    {
      "image": "https://opgg-static.akamaized.net/meta/images/lol/15.19.1/champion/Lillia.png?image=c_crop,h_103,w_103,x_9,y_9/q_auto:good,f_png,w_160,h_160&v=1519",
      "name": "含羞蓓蕾",
      "id": 24
    },
    {
      "image": "https://opgg-static.akamaized.net/meta/images/lol/15.19.1/champion/Nami.png?image=c_crop,h_103,w_103,x_9,y_9/q_auto:good,f_png,w_160,h_160&v=1519",
      "name": "唤潮鲛姬",
      "id": 25
    },
    {
      "image": "https://opgg-static.akamaized.net/meta/images/lol/15.19.1/champion/Lucian.png?image=c_crop,h_103,w_103,x_9,y_9/q_auto:good,f_png,w_160,h_160&v=1519",
      "name": "圣枪游侠",
      "id": 26
    },
    {
      "image": "https://opgg-static.akamaized.net/meta/images/lol/15.19.1/champion/Poppy.png?image=c_crop,h_103,w_103,x_9,y_9/q_auto:good,f_png,w_160,h_160&v=1519",
      "name": "圣锤之毅",
      "id": 27
    },
    {
      "image": "https://opgg-static.akamaized.net/meta/images/lol/15.19.1/champion/Morgana.png?image=c_crop,h_103,w_103,x_9,y_9/q_auto:good,f_png,w_160,h_160&v=1519",
      "name": "堕落天使",
      "id": 28
    },
    {
      "image": "https://opgg-static.akamaized.net/meta/images/lol/15.19.1/champion/Kalista.png?image=c_crop,h_103,w_103,x_9,y_9/q_auto:good,f_png,w_160,h_160&v=1519",
      "name": "复仇之矛",
      "id": 29
    },
    {
      "image": "https://opgg-static.akamaized.net/meta/images/lol/15.19.1/champion/Brand.png?image=c_crop,h_103,w_103,x_9,y_9/q_auto:good,f_png,w_160,h_160&v=1519",
      "name": "复仇焰魂",
      "id": 30
    },
    {
      "image": "https://opgg-static.akamaized.net/meta/images/lol/15.19.1/champion/Heimerdinger.png?image=c_crop,h_103,w_103,x_9,y_9/q_auto:good,f_png,w_160,h_160&v=1519",
      "name": "大发明家",
      "id": 31
    },
    {
      "image": "https://opgg-static.akamaized.net/meta/images/lol/15.19.1/champion/Karma.png?image=c_crop,h_103,w_103,x_9,y_9/q_auto:good,f_png,w_160,h_160&v=1519",
      "name": "天启者",
      "id": 32
    },
    {
      "image": "https://opgg-static.akamaized.net/meta/images/lol/15.19.1/champion/Viktor.png?image=c_crop,h_103,w_103,x_9,y_9/q_auto:good,f_png,w_160,h_160&v=1519",
      "name": "奥术先驱",
      "id": 33
    },
    {
      "image": "https://opgg-static.akamaized.net/meta/images/lol/15.19.1/champion/Ashe.png?image=c_crop,h_103,w_103,x_9,y_9/q_auto:good,f_png,w_160,h_160&v=1519",
      "name": "寒冰射手",
      "id": 34
    },
    {
      "image": "https://opgg-static.akamaized.net/meta/images/lol/15.19.1/champion/Yone.png?image=c_crop,h_103,w_103,x_9,y_9/q_auto:good,f_png,w_160,h_160&v=1519",
      "name": "封魔剑魂",
      "id": 35
    },
    {
      "image": "https://opgg-static.akamaized.net/meta/images/lol/15.19.1/champion/Ornn.png?image=c_crop,h_103,w_103,x_9,y_9/q_auto:good,f_png,w_160,h_160&v=1519",
      "name": "山隐之焰",
      "id": 36
    },
    {
      "image": "https://opgg-static.akamaized.net/meta/images/lol/15.19.1/champion/Taliyah.png?image=c_crop,h_103,w_103,x_9,y_9/q_auto:good,f_png,w_160,h_160&v=1519",
      "name": "岩雀",
      "id": 37
    },
    {
      "image": "https://opgg-static.akamaized.net/meta/images/lol/15.19.1/champion/Trundle.png?image=c_crop,h_103,w_103,x_9,y_9/q_auto:good,f_png,w_160,h_160&v=1519",
      "name": "巨魔之王",
      "id": 38
    },
    {
      "image": "https://opgg-static.akamaized.net/meta/images/lol/15.19.1/champion/Rakan.png?image=c_crop,h_103,w_103,x_9,y_9/q_auto:good,f_png,w_160,h_160&v=1519",
      "name": "幻翎",
      "id": 39
    },
    {
      "image": "https://opgg-static.akamaized.net/meta/images/lol/15.19.1/champion/Hwei.png?image=c_crop,h_103,w_103,x_9,y_9/q_auto:good,f_png,w_160,h_160&v=1519",
      "name": "异画师",
      "id": 40
    },
    {
      "image": "https://opgg-static.akamaized.net/meta/images/lol/15.19.1/champion/Braum.png?image=c_crop,h_103,w_103,x_9,y_9/q_auto:good,f_png,w_160,h_160&v=1519",
      "name": "弗雷尔卓德之心",
      "id": 41
    },
    {
      "image": "https://opgg-static.akamaized.net/meta/images/lol/15.19.1/champion/Akshan.png?image=c_crop,h_103,w_103,x_9,y_9/q_auto:good,f_png,w_160,h_160&v=1519",
      "name": "影哨",
      "id": 42
    },
    {
      "image": "https://opgg-static.akamaized.net/meta/images/lol/15.19.1/champion/Zed.png?image=c_crop,h_103,w_103,x_9,y_9/q_auto:good,f_png,w_160,h_160&v=1519",
      "name": "影流之主",
      "id": 43
    },
    {
      "image": "https://opgg-static.akamaized.net/meta/images/lol/15.19.1/champion/Kayn.png?image=c_crop,h_103,w_103,x_9,y_9/q_auto:good,f_png,w_160,h_160&v=1519",
      "name": "影流之镰",
      "id": 44
    },
    {
      "image": "https://opgg-static.akamaized.net/meta/images/lol/15.19.1/champion/Garen.png?image=c_crop,h_103,w_103,x_9,y_9/q_auto:good,f_png,w_160,h_160&v=1519",
      "name": "德玛西亚之力",
      "id": 45
    },
    {
      "image": "https://opgg-static.akamaized.net/meta/images/lol/15.19.1/champion/Quinn.png?image=c_crop,h_103,w_103,x_9,y_9/q_auto:good,f_png,w_160,h_160&v=1519",
      "name": "德玛西亚之翼",
      "id": 46
    },
    {
      "image": "https://opgg-static.akamaized.net/meta/images/lol/15.19.1/champion/JarvanIV.png?image=c_crop,h_103,w_103,x_9,y_9/q_auto:good,f_png,w_160,h_160&v=1519",
      "name": "德玛西亚皇子",
      "id": 47
    },
    {
      "image": "https://opgg-static.akamaized.net/meta/images/lol/15.19.1/champion/XinZhao.png?image=c_crop,h_103,w_103,x_9,y_9/q_auto:good,f_png,w_160,h_160&v=1519",
      "name": "德邦总管",
      "id": 48
    },
    {
      "image": "https://opgg-static.akamaized.net/meta/images/lol/15.19.1/champion/Shaco.png?image=c_crop,h_103,w_103,x_9,y_9/q_auto:good,f_png,w_160,h_160&v=1519",
      "name": "恶魔小丑",
      "id": 49
    },
    {
      "image": "https://opgg-static.akamaized.net/meta/images/lol/15.19.1/champion/Varus.png?image=c_crop,h_103,w_103,x_9,y_9/q_auto:good,f_png,w_160,h_160&v=1519",
      "name": "惩戒之箭",
      "id": 50
    },
    {
      "image": "https://opgg-static.akamaized.net/meta/images/lol/15.19.1/champion/Vex.png?image=c_crop,h_103,w_103,x_9,y_9/q_auto:good,f_png,w_160,h_160&v=1519",
      "name": "愁云使者",
      "id": 51
    },
    {
      "image": "https://opgg-static.akamaized.net/meta/images/lol/15.19.1/champion/Jhin.png?image=c_crop,h_103,w_103,x_9,y_9/q_auto:good,f_png,w_160,h_160&v=1519",
      "name": "戏命师",
      "id": 52
    },
    {
      "image": "https://opgg-static.akamaized.net/meta/images/lol/15.19.1/champion/Hecarim.png?image=c_crop,h_103,w_103,x_9,y_9/q_auto:good,f_png,w_160,h_160&v=1519",
      "name": "战争之影",
      "id": 53
    },
    {
      "image": "https://opgg-static.akamaized.net/meta/images/lol/15.19.1/champion/Sivir.png?image=c_crop,h_103,w_103,x_9,y_9/q_auto:good,f_png,w_160,h_160&v=1519",
      "name": "战争女神",
      "id": 54
    },
    {
      "image": "https://opgg-static.akamaized.net/meta/images/lol/15.19.1/champion/Maokai.png?image=c_crop,h_103,w_103,x_9,y_9/q_auto:good,f_png,w_160,h_160&v=1519",
      "name": "扭曲树精",
      "id": 55
    },
    {
      "image": "https://opgg-static.akamaized.net/meta/images/lol/15.19.1/champion/Rammus.png?image=c_crop,h_103,w_103,x_9,y_9/q_auto:good,f_png,w_160,h_160&v=1519",
      "name": "披甲龙龟",
      "id": 56
    },
    {
      "image": "https://opgg-static.akamaized.net/meta/images/lol/15.19.1/champion/Ezreal.png?image=c_crop,h_103,w_103,x_9,y_9/q_auto:good,f_png,w_160,h_160&v=1519",
      "name": "探险家",
      "id": 57
    },
    {
      "image": "https://opgg-static.akamaized.net/meta/images/lol/15.19.1/champion/Riven.png?image=c_crop,h_103,w_103,x_9,y_9/q_auto:good,f_png,w_160,h_160&v=1519",
      "name": "放逐之刃",
      "id": 58
    },
    {
      "image": "https://opgg-static.akamaized.net/meta/images/lol/15.19.1/champion/Fiora.png?image=c_crop,h_103,w_103,x_9,y_9/q_auto:good,f_png,w_160,h_160&v=1519",
      "name": "无双剑姬",
      "id": 59
    },
    {
      "image": "https://opgg-static.akamaized.net/meta/images/lol/15.19.1/champion/MasterYi.png?image=c_crop,h_103,w_103,x_9,y_9/q_auto:good,f_png,w_160,h_160&v=1519",
      "name": "无极剑圣",
      "id": 60
    },
    {
      "image": "https://opgg-static.akamaized.net/meta/images/lol/15.19.1/champion/Urgot.png?image=c_crop,h_103,w_103,x_9,y_9/q_auto:good,f_png,w_160,h_160&v=1519",
      "name": "无畏战车",
      "id": 61
    },
    {
      "image": "https://opgg-static.akamaized.net/meta/images/lol/15.19.1/champion/Zilean.png?image=c_crop,h_103,w_103,x_9,y_9/q_auto:good,f_png,w_160,h_160&v=1519",
      "name": "时光守护者",
      "id": 62
    },
    {
      "image": "https://opgg-static.akamaized.net/meta/images/lol/15.19.1/champion/Ekko.png?image=c_crop,h_103,w_103,x_9,y_9/q_auto:good,f_png,w_160,h_160&v=1519",
      "name": "时间刺客",
      "id": 63
    },
    {
      "image": "https://opgg-static.akamaized.net/meta/images/lol/15.19.1/champion/Milio.png?image=c_crop,h_103,w_103,x_9,y_9/q_auto:good,f_png,w_160,h_160&v=1519",
      "name": "明烛",
      "id": 64
    },
    {
      "image": "https://opgg-static.akamaized.net/meta/images/lol/15.19.1/champion/Bard.png?image=c_crop,h_103,w_103,x_9,y_9/q_auto:good,f_png,w_160,h_160&v=1519",
      "name": "星界游神",
      "id": 65
    },
    {
      "image": "https://opgg-static.akamaized.net/meta/images/lol/15.19.1/champion/Seraphine.png?image=c_crop,h_103,w_103,x_9,y_9/q_auto:good,f_png,w_160,h_160&v=1519",
      "name": "星籁歌姬",
      "id": 66
    },
    {
      "image": "https://opgg-static.akamaized.net/meta/images/lol/15.19.1/champion/Vayne.png?image=c_crop,h_103,w_103,x_9,y_9/q_auto:good,f_png,w_160,h_160&v=1519",
      "name": "暗夜猎手",
      "id": 67
    },
    {
      "image": "https://opgg-static.akamaized.net/meta/images/lol/15.19.1/champion/Aatrox.png?image=c_crop,h_103,w_103,x_9,y_9/q_auto:good,f_png,w_160,h_160&v=1519",
      "name": "暗裔剑魔",
      "id": 68
    },
    {
      "image": "https://opgg-static.akamaized.net/meta/images/lol/15.19.1/champion/Syndra.png?image=c_crop,h_103,w_103,x_9,y_9/q_auto:good,f_png,w_160,h_160&v=1519",
      "name": "暗黑元首",
      "id": 69
    },
    {
      "image": "https://opgg-static.akamaized.net/meta/images/lol/15.19.1/champion/Shen.png?image=c_crop,h_103,w_103,x_9,y_9/q_auto:good,f_png,w_160,h_160&v=1519",
      "name": "暮光之眼",
      "id": 70
    },
    {
      "image": "https://opgg-static.akamaized.net/meta/images/lol/15.19.1/champion/Zoe.png?image=c_crop,h_103,w_103,x_9,y_9/q_auto:good,f_png,w_160,h_160&v=1519",
      "name": "暮光星灵",
      "id": 71
    },
    {
      "image": "https://opgg-static.akamaized.net/meta/images/lol/15.19.1/champion/Kled.png?image=c_crop,h_103,w_103,x_9,y_9/q_auto:good,f_png,w_160,h_160&v=1519",
      "name": "暴怒骑士",
      "id": 72
    },
    {
      "image": "https://opgg-static.akamaized.net/meta/images/lol/15.19.1/champion/Jinx.png?image=c_crop,h_103,w_103,x_9,y_9/q_auto:good,f_png,w_160,h_160&v=1519",
      "name": "暴走萝莉",
      "id": 73
    },
    {
      "image": "https://opgg-static.akamaized.net/meta/images/lol/15.19.1/champion/Leona.png?image=c_crop,h_103,w_103,x_9,y_9/q_auto:good,f_png,w_160,h_160&v=1519",
      "name": "曙光女神",
      "id": 74
    },
    {
      "image": "https://opgg-static.akamaized.net/meta/images/lol/15.19.1/champion/Jayce.png?image=c_crop,h_103,w_103,x_9,y_9/q_auto:good,f_png,w_160,h_160&v=1519",
      "name": "未来守护者",
      "id": 75
    },
    {
      "image": "https://opgg-static.akamaized.net/meta/images/lol/15.19.1/champion/Rumble.png?image=c_crop,h_103,w_103,x_9,y_9/q_auto:good,f_png,w_160,h_160&v=1519",
      "name": "机械公敌",
      "id": 76
    },
    {
      "image": "https://opgg-static.akamaized.net/meta/images/lol/15.19.1/champion/Kayle.png?image=c_crop,h_103,w_103,x_9,y_9/q_auto:good,f_png,w_160,h_160&v=1519",
      "name": "正义天使",
      "id": 77
    },
    {
      "image": "https://opgg-static.akamaized.net/meta/images/lol/15.19.1/champion/Galio.png?image=c_crop,h_103,w_103,x_9,y_9/q_auto:good,f_png,w_160,h_160&v=1519",
      "name": "正义巨像",
      "id": 78
    },
    {
      "image": "https://opgg-static.akamaized.net/meta/images/lol/15.19.1/champion/Jax.png?image=c_crop,h_103,w_103,x_9,y_9/q_auto:good,f_png,w_160,h_160&v=1519",
      "name": "武器大师",
      "id": 79
    },
    {
      "image": "https://opgg-static.akamaized.net/meta/images/lol/15.19.1/champion/Karthus.png?image=c_crop,h_103,w_103,x_9,y_9/q_auto:good,f_png,w_160,h_160&v=1519",
      "name": "死亡颂唱者",
      "id": 80
    },
    {
      "image": "https://opgg-static.akamaized.net/meta/images/lol/15.19.1/champion/Amumu.png?image=c_crop,h_103,w_103,x_9,y_9/q_auto:good,f_png,w_160,h_160&v=1519",
      "name": "殇之木乃伊",
      "id": 81
    },
    {
      "image": "https://opgg-static.akamaized.net/meta/images/lol/15.19.1/champion/Aphelios.png?image=c_crop,h_103,w_103,x_9,y_9/q_auto:good,f_png,w_160,h_160&v=1519",
      "name": "残月之肃",
      "id": 82
    },
    {
      "image": "https://opgg-static.akamaized.net/meta/images/lol/15.19.1/champion/Nocturne.png?image=c_crop,h_103,w_103,x_9,y_9/q_auto:good,f_png,w_160,h_160&v=1519",
      "name": "永恒梦魇",
      "id": 83
    },
    {
      "image": "https://opgg-static.akamaized.net/meta/images/lol/15.19.1/champion/Kindred.png?image=c_crop,h_103,w_103,x_9,y_9/q_auto:good,f_png,w_160,h_160&v=1519",
      "name": "永猎双子",
      "id": 84
    },
    {
      "image": "https://opgg-static.akamaized.net/meta/images/lol/15.19.1/champion/Nasus.png?image=c_crop,h_103,w_103,x_9,y_9/q_auto:good,f_png,w_160,h_160&v=1519",
      "name": "沙漠死神",
      "id": 85
    },
    {
      "image": "https://opgg-static.akamaized.net/meta/images/lol/15.19.1/champion/Samira.png?image=c_crop,h_103,w_103,x_9,y_9/q_auto:good,f_png,w_160,h_160&v=1519",
      "name": "沙漠玫瑰",
      "id": 86
    },
    {
      "image": "https://opgg-static.akamaized.net/meta/images/lol/15.19.1/champion/Azir.png?image=c_crop,h_103,w_103,x_9,y_9/q_auto:good,f_png,w_160,h_160&v=1519",
      "name": "沙漠皇帝",
      "id": 87
    },
    {
      "image": "https://opgg-static.akamaized.net/meta/images/lol/15.19.1/champion/TahmKench.png?image=c_crop,h_103,w_103,x_9,y_9/q_auto:good,f_png,w_160,h_160&v=1519",
      "name": "河流之王",
      "id": 88
    },
    {
      "image": "https://opgg-static.akamaized.net/meta/images/lol/15.19.1/champion/Graves.png?image=c_crop,h_103,w_103,x_9,y_9/q_auto:good,f_png,w_160,h_160&v=1519",
      "name": "法外狂徒",
      "id": 89
    },
    {
      "image": "https://opgg-static.akamaized.net/meta/images/lol/15.19.1/champion/Mel.png?image=c_crop,h_103,w_103,x_9,y_9/q_auto:good,f_png,w_160,h_160&v=1519",
      "name": "流光镜影",
      "id": 90
    },
    {
      "image": "https://opgg-static.akamaized.net/meta/images/lol/15.19.1/champion/Illaoi.png?image=c_crop,h_103,w_103,x_9,y_9/q_auto:good,f_png,w_160,h_160&v=1519",
      "name": "海兽祭司",
      "id": 91
    },
    {
      "image": "https://opgg-static.akamaized.net/meta/images/lol/15.19.1/champion/Gangplank.png?image=c_crop,h_103,w_103,x_9,y_9/q_auto:good,f_png,w_160,h_160&v=1519",
      "name": "海洋之灾",
      "id": 92
    },
    {
      "image": "https://opgg-static.akamaized.net/meta/images/lol/15.19.1/champion/Senna.png?image=c_crop,h_103,w_103,x_9,y_9/q_auto:good,f_png,w_160,h_160&v=1519",
      "name": "涤魂圣枪",
      "id": 93
    },
    {
      "image": "https://opgg-static.akamaized.net/meta/images/lol/15.19.1/champion/Nautilus.png?image=c_crop,h_103,w_103,x_9,y_9/q_auto:good,f_png,w_160,h_160&v=1519",
      "name": "深海泰坦",
      "id": 94
    },
    {
      "image": "https://opgg-static.akamaized.net/meta/images/lol/15.19.1/champion/KogMaw.png?image=c_crop,h_103,w_103,x_9,y_9/q_auto:good,f_png,w_160,h_160&v=1519",
      "name": "深渊巨口",
      "id": 95
    },
    {
      "image": "https://opgg-static.akamaized.net/meta/images/lol/15.19.1/champion/Fizz.png?image=c_crop,h_103,w_103,x_9,y_9/q_auto:good,f_png,w_160,h_160&v=1519",
      "name": "潮汐海灵",
      "id": 96
    },
    {
      "image": "https://opgg-static.akamaized.net/meta/images/lol/15.19.1/champion/Gwen.png?image=c_crop,h_103,w_103,x_9,y_9/q_auto:good,f_png,w_160,h_160&v=1519",
      "name": "灵罗娃娃",
      "id": 97
    },
    {
      "image": "https://opgg-static.akamaized.net/meta/images/lol/15.19.1/champion/Singed.png?image=c_crop,h_103,w_103,x_9,y_9/q_auto:good,f_png,w_160,h_160&v=1519",
      "name": "炼金术士",
      "id": 98
    },
    {
      "image": "https://opgg-static.akamaized.net/meta/images/lol/15.19.1/champion/Renata.png?image=c_crop,h_103,w_103,x_9,y_9/q_auto:good,f_png,w_160,h_160&v=1519",
      "name": "炼金男爵",
      "id": 99
    },
    {
      "image": "https://opgg-static.akamaized.net/meta/images/lol/15.19.1/champion/Smolder.png?image=c_crop,h_103,w_103,x_9,y_9/q_auto:good,f_png,w_160,h_160&v=1519",
      "name": "炽炎雏龙",
      "id": 100
    },
    {
      "image": "https://opgg-static.akamaized.net/meta/images/lol/15.19.1/champion/Malphite.png?image=c_crop,h_103,w_103,x_9,y_9/q_auto:good,f_png,w_160,h_160&v=1519",
      "name": "熔岩巨兽",
      "id": 101
    },
    {
      "image": "https://opgg-static.akamaized.net/meta/images/lol/15.19.1/champion/Blitzcrank.png?image=c_crop,h_103,w_103,x_9,y_9/q_auto:good,f_png,w_160,h_160&v=1519",
      "name": "蒸汽机器人",
      "id": 102
    },
    {
      "image": "https://opgg-static.akamaized.net/meta/images/lol/15.19.1/champion/Ziggs.png?image=c_crop,h_103,w_103,x_9,y_9/q_auto:good,f_png,w_160,h_160&v=1519",
      "name": "爆破鬼才",
      "id": 103
    },
    {
      "image": "https://opgg-static.akamaized.net/meta/images/lol/15.19.1/champion/Alistar.png?image=c_crop,h_103,w_103,x_9,y_9/q_auto:good,f_png,w_160,h_160&v=1519",
      "name": "牛头酋长",
      "id": 104
    },
    {
      "image": "https://opgg-static.akamaized.net/meta/images/lol/15.19.1/champion/Yorick.png?image=c_crop,h_103,w_103,x_9,y_9/q_auto:good,f_png,w_160,h_160&v=1519",
      "name": "牧魂人",
      "id": 105
    },
    {
      "image": "https://opgg-static.akamaized.net/meta/images/lol/15.19.1/champion/Briar.png?image=c_crop,h_103,w_103,x_9,y_9/q_auto:good,f_png,w_160,h_160&v=1519",
      "name": "狂厄蔷薇",
      "id": 106
    },
    {
      "image": "https://opgg-static.akamaized.net/meta/images/lol/15.19.1/champion/Olaf.png?image=c_crop,h_103,w_103,x_9,y_9/q_auto:good,f_png,w_160,h_160&v=1519",
      "name": "狂战士",
      "id": 107
    },
    {
      "image": "https://opgg-static.akamaized.net/meta/images/lol/15.19.1/champion/Kennen.png?image=c_crop,h_103,w_103,x_9,y_9/q_auto:good,f_png,w_160,h_160&v=1519",
      "name": "狂暴之心",
      "id": 108
    },
    {
      "image": "https://opgg-static.akamaized.net/meta/images/lol/15.19.1/champion/Nidalee.png?image=c_crop,h_103,w_103,x_9,y_9/q_auto:good,f_png,w_160,h_160&v=1519",
      "name": "狂野女猎手",
      "id": 109
    },
    {
      "image": "https://opgg-static.akamaized.net/meta/images/lol/15.19.1/champion/Vladimir.png?image=c_crop,h_103,w_103,x_9,y_9/q_auto:good,f_png,w_160,h_160&v=1519",
      "name": "猩红收割者",
      "id": 110
    },
    {
      "image": "https://opgg-static.akamaized.net/meta/images/lol/15.19.1/champion/Sona.png?image=c_crop,h_103,w_103,x_9,y_9/q_auto:good,f_png,w_160,h_160&v=1519",
      "name": "琴瑟仙女",
      "id": 111
    },
    {
      "image": "https://opgg-static.akamaized.net/meta/images/lol/15.19.1/champion/Taric.png?image=c_crop,h_103,w_103,x_9,y_9/q_auto:good,f_png,w_160,h_160&v=1519",
      "name": "瓦洛兰之盾",
      "id": 112
    },
    {
      "image": "https://opgg-static.akamaized.net/meta/images/lol/15.19.1/champion/Zac.png?image=c_crop,h_103,w_103,x_9,y_9/q_auto:good,f_png,w_160,h_160&v=1519",
      "name": "生化魔人",
      "id": 113
    },
    {
      "image": "https://opgg-static.akamaized.net/meta/images/lol/15.19.1/champion/Yasuo.png?image=c_crop,h_103,w_103,x_9,y_9/q_auto:good,f_png,w_160,h_160&v=1519",
      "name": "疾风剑豪",
      "id": 114
    },
    {
      "image": "https://opgg-static.akamaized.net/meta/images/lol/15.19.1/champion/Evelynn.png?image=c_crop,h_103,w_103,x_9,y_9/q_auto:good,f_png,w_160,h_160&v=1519",
      "name": "痛苦之拥",
      "id": 115
    },
    {
      "image": "https://opgg-static.akamaized.net/meta/images/lol/15.19.1/champion/Twitch.png?image=c_crop,h_103,w_103,x_9,y_9/q_auto:good,f_png,w_160,h_160&v=1519",
      "name": "瘟疫之源",
      "id": 116
    },
    {
      "image": "https://opgg-static.akamaized.net/meta/images/lol/15.19.1/champion/Naafiri.png?image=c_crop,h_103,w_103,x_9,y_9/q_auto:good,f_png,w_160,h_160&v=1519",
      "name": "百裂冥犬",
      "id": 117
    },
    {
      "image": "https://opgg-static.akamaized.net/meta/images/lol/15.19.1/champion/Diana.png?image=c_crop,h_103,w_103,x_9,y_9/q_auto:good,f_png,w_160,h_160&v=1519",
      "name": "皎月女神",
      "id": 118
    },
    {
      "image": "https://opgg-static.akamaized.net/meta/images/lol/15.19.1/champion/Caitlyn.png?image=c_crop,h_103,w_103,x_9,y_9/q_auto:good,f_png,w_160,h_160&v=1519",
      "name": "皮城女警",
      "id": 119
    },
    {
      "image": "https://opgg-static.akamaized.net/meta/images/lol/15.19.1/champion/Vi.png?image=c_crop,h_103,w_103,x_9,y_9/q_auto:good,f_png,w_160,h_160&v=1519",
      "name": "皮城执法官",
      "id": 120
    },
    {
      "image": "https://opgg-static.akamaized.net/meta/images/lol/15.19.1/champion/LeeSin.png?image=c_crop,h_103,w_103,x_9,y_9/q_auto:good,f_png,w_160,h_160&v=1519",
      "name": "盲僧",
      "id": 121
    },
    {
      "image": "https://opgg-static.akamaized.net/meta/images/lol/15.19.1/champion/Viego.png?image=c_crop,h_103,w_103,x_9,y_9/q_auto:good,f_png,w_160,h_160&v=1519",
      "name": "破败之王",
      "id": 122
    },
    {
      "image": "https://opgg-static.akamaized.net/meta/images/lol/15.19.1/champion/Warwick.png?image=c_crop,h_103,w_103,x_9,y_9/q_auto:good,f_png,w_160,h_160&v=1519",
      "name": "祖安怒兽",
      "id": 123
    },
    {
      "image": "https://opgg-static.akamaized.net/meta/images/lol/15.19.1/champion/DrMundo.png?image=c_crop,h_103,w_103,x_9,y_9/q_auto:good,f_png,w_160,h_160&v=1519",
      "name": "祖安狂人",
      "id": 124
    },
    {
      "image": "https://opgg-static.akamaized.net/meta/images/lol/15.19.1/champion/Zeri.png?image=c_crop,h_103,w_103,x_9,y_9/q_auto:good,f_png,w_160,h_160&v=1519",
      "name": "祖安花火",
      "id": 125
    },
    {
      "image": "https://opgg-static.akamaized.net/meta/images/lol/15.19.1/champion/Akali.png?image=c_crop,h_103,w_103,x_9,y_9/q_auto:good,f_png,w_160,h_160&v=1519",
      "name": "离群之刺",
      "id": 126
    },
    {
      "image": "https://opgg-static.akamaized.net/meta/images/lol/15.19.1/champion/Ryze.png?image=c_crop,h_103,w_103,x_9,y_9/q_auto:good,f_png,w_160,h_160&v=1519",
      "name": "符文法师",
      "id": 127
    },
    {
      "image": "https://opgg-static.akamaized.net/meta/images/lol/15.19.1/champion/KSante.png?image=c_crop,h_103,w_103,x_9,y_9/q_auto:good,f_png,w_160,h_160&v=1519",
      "name": "纳祖芒荣耀",
      "id": 128
    },
    {
      "image": "https://opgg-static.akamaized.net/meta/images/lol/15.19.1/champion/Ivern.png?image=c_crop,h_103,w_103,x_9,y_9/q_auto:good,f_png,w_160,h_160&v=1519",
      "name": "翠神",
      "id": 129
    },
    {
      "image": "https://opgg-static.akamaized.net/meta/images/lol/15.19.1/champion/Sett.png?image=c_crop,h_103,w_103,x_9,y_9/q_auto:good,f_png,w_160,h_160&v=1519",
      "name": "腕豪",
      "id": 130
    },
    {
      "image": "https://opgg-static.akamaized.net/meta/images/lol/15.19.1/champion/Corki.png?image=c_crop,h_103,w_103,x_9,y_9/q_auto:good,f_png,w_160,h_160&v=1519",
      "name": "英勇投弹手",
      "id": 131
    },
    {
      "image": "https://opgg-static.akamaized.net/meta/images/lol/15.19.1/champion/Zyra.png?image=c_crop,h_103,w_103,x_9,y_9/q_auto:good,f_png,w_160,h_160&v=1519",
      "name": "荆棘之兴",
      "id": 132
    },
    {
      "image": "https://opgg-static.akamaized.net/meta/images/lol/15.19.1/champion/Renekton.png?image=c_crop,h_103,w_103,x_9,y_9/q_auto:good,f_png,w_160,h_160&v=1519",
      "name": "荒漠屠夫",
      "id": 133
    },
    {
      "image": "https://opgg-static.akamaized.net/meta/images/lol/15.19.1/champion/Draven.png?image=c_crop,h_103,w_103,x_9,y_9/q_auto:good,f_png,w_160,h_160&v=1519",
      "name": "荣耀行刑官",
      "id": 134
    },
    {
      "image": "https://opgg-static.akamaized.net/meta/images/lol/15.19.1/champion/Kaisa.png?image=c_crop,h_103,w_103,x_9,y_9/q_auto:good,f_png,w_160,h_160&v=1519",
      "name": "虚空之女",
      "id": 135
    },
    {
      "image": "https://opgg-static.akamaized.net/meta/images/lol/15.19.1/champion/Velkoz.png?image=c_crop,h_103,w_103,x_9,y_9/q_auto:good,f_png,w_160,h_160&v=1519",
      "name": "虚空之眼",
      "id": 136
    },
    {
      "image": "https://opgg-static.akamaized.net/meta/images/lol/15.19.1/champion/Malzahar.png?image=c_crop,h_103,w_103,x_9,y_9/q_auto:good,f_png,w_160,h_160&v=1519",
      "name": "虚空先知",
      "id": 137
    },
    {
      "image": "https://opgg-static.akamaized.net/meta/images/lol/15.19.1/champion/Belveth.png?image=c_crop,h_103,w_103,x_9,y_9/q_auto:good,f_png,w_160,h_160&v=1519",
      "name": "虚空女皇",
      "id": 138
    },
    {
      "image": "https://opgg-static.akamaized.net/meta/images/lol/15.19.1/champion/Chogath.png?image=c_crop,h_103,w_103,x_9,y_9/q_auto:good,f_png,w_160,h_160&v=1519",
      "name": "虚空恐惧",
      "id": 139
    },
    {
      "image": "https://opgg-static.akamaized.net/meta/images/lol/15.19.1/champion/Khazix.png?image=c_crop,h_103,w_103,x_9,y_9/q_auto:good,f_png,w_160,h_160&v=1519",
      "name": "虚空掠夺者",
      "id": 140
    },
    {
      "image": "https://opgg-static.akamaized.net/meta/images/lol/15.19.1/champion/Kassadin.png?image=c_crop,h_103,w_103,x_9,y_9/q_auto:good,f_png,w_160,h_160&v=1519",
      "name": "虚空行者",
      "id": 141
    },
    {
      "image": "https://opgg-static.akamaized.net/meta/images/lol/15.19.1/champion/RekSai.png?image=c_crop,h_103,w_103,x_9,y_9/q_auto:good,f_png,w_160,h_160&v=1519",
      "name": "虚空遁地兽",
      "id": 142
    },
    {
      "image": "https://opgg-static.akamaized.net/meta/images/lol/15.19.1/champion/Tryndamere.png?image=c_crop,h_103,w_103,x_9,y_9/q_auto:good,f_png,w_160,h_160&v=1519",
      "name": "蛮族之王",
      "id": 143
    },
    {
      "image": "https://opgg-static.akamaized.net/meta/images/lol/15.19.1/champion/Elise.png?image=c_crop,h_103,w_103,x_9,y_9/q_auto:good,f_png,w_160,h_160&v=1519",
      "name": "蜘蛛女皇",
      "id": 144
    },
    {
      "image": "https://opgg-static.akamaized.net/meta/images/lol/15.19.1/champion/Pyke.png?image=c_crop,h_103,w_103,x_9,y_9/q_auto:good,f_png,w_160,h_160&v=1519",
      "name": "血港鬼影",
      "id": 145
    },
    {
      "image": "https://opgg-static.akamaized.net/meta/images/lol/15.19.1/champion/Sylas.png?image=c_crop,h_103,w_103,x_9,y_9/q_auto:good,f_png,w_160,h_160&v=1519",
      "name": "解脱者",
      "id": 146
    },
    {
      "image": "https://opgg-static.akamaized.net/meta/images/lol/15.19.1/champion/Leblanc.png?image=c_crop,h_103,w_103,x_9,y_9/q_auto:good,f_png,w_160,h_160&v=1519",
      "name": "诡术妖姬",
      "id": 147
    },
    {
      "image": "https://opgg-static.akamaized.net/meta/images/lol/15.19.1/champion/Darius.png?image=c_crop,h_103,w_103,x_9,y_9/q_auto:good,f_png,w_160,h_160&v=1519",
      "name": "诺克萨斯之手",
      "id": 148
    },
    {
      "image": "https://opgg-static.akamaized.net/meta/images/lol/15.19.1/champion/Swain.png?image=c_crop,h_103,w_103,x_9,y_9/q_auto:good,f_png,w_160,h_160&v=1519",
      "name": "诺克萨斯统领",
      "id": 149
    },
    {
      "image": "https://opgg-static.akamaized.net/meta/images/lol/15.19.1/champion/MissFortune.png?image=c_crop,h_103,w_103,x_9,y_9/q_auto:good,f_png,w_160,h_160&v=1519",
      "name": "赏金猎人",
      "id": 150
    },
    {
      "image": "https://opgg-static.akamaized.net/meta/images/lol/15.19.1/champion/Teemo.png?image=c_crop,h_103,w_103,x_9,y_9/q_auto:good,f_png,w_160,h_160&v=1519",
      "name": "迅捷斥候",
      "id": 151
    },
    {
      "image": "https://opgg-static.akamaized.net/meta/images/lol/15.19.1/champion/Xerath.png?image=c_crop,h_103,w_103,x_9,y_9/q_auto:good,f_png,w_160,h_160&v=1519",
      "name": "远古巫灵",
      "id": 152
    },
    {
      "image": "https://opgg-static.akamaized.net/meta/images/lol/15.19.1/champion/Fiddlesticks.png?image=c_crop,h_103,w_103,x_9,y_9/q_auto:good,f_png,w_160,h_160&v=1519",
      "name": "远古恐惧",
      "id": 153
    },
    {
      "image": "https://opgg-static.akamaized.net/meta/images/lol/15.19.1/champion/Gnar.png?image=c_crop,h_103,w_103,x_9,y_9/q_auto:good,f_png,w_160,h_160&v=1519",
      "name": "迷失之牙",
      "id": 154
    },
    {
      "image": "https://opgg-static.akamaized.net/meta/images/lol/15.19.1/champion/Xayah.png?image=c_crop,h_103,w_103,x_9,y_9/q_auto:good,f_png,w_160,h_160&v=1519",
      "name": "逆羽",
      "id": 155
    },
    {
      "image": "https://opgg-static.akamaized.net/meta/images/lol/15.19.1/champion/Veigar.png?image=c_crop,h_103,w_103,x_9,y_9/q_auto:good,f_png,w_160,h_160&v=1519",
      "name": "邪恶小法师",
      "id": 156
    },
    {
      "image": "https://opgg-static.akamaized.net/meta/images/lol/15.19.1/champion/Gragas.png?image=c_crop,h_103,w_103,x_9,y_9/q_auto:good,f_png,w_160,h_160&v=1519",
      "name": "酒桶",
      "id": 157
    },
    {
      "image": "https://opgg-static.akamaized.net/meta/images/lol/15.19.1/champion/Ambessa.png?image=c_crop,h_103,w_103,x_9,y_9/q_auto:good,f_png,w_160,h_160&v=1519",
      "name": "铁血狼母",
      "id": 158
    },
    {
      "image": "https://opgg-static.akamaized.net/meta/images/lol/15.19.1/champion/Mordekaiser.png?image=c_crop,h_103,w_103,x_9,y_9/q_auto:good,f_png,w_160,h_160&v=1519",
      "name": "铁铠冥魂",
      "id": 159
    },
    {
      "image": "https://opgg-static.akamaized.net/meta/images/lol/15.19.1/champion/AurelionSol.png?image=c_crop,h_103,w_103,x_9,y_9/q_auto:good,f_png,w_160,h_160&v=1519",
      "name": "铸星龙王",
      "id": 160
    },
    {
      "image": "https://opgg-static.akamaized.net/meta/images/lol/15.19.1/champion/Rell.png?image=c_crop,h_103,w_103,x_9,y_9/q_auto:good,f_png,w_160,h_160&v=1519",
      "name": "镕铁少女",
      "id": 161
    },
    {
      "image": "https://opgg-static.akamaized.net/meta/images/lol/15.19.1/champion/Nunu.png?image=c_crop,h_103,w_103,x_9,y_9/q_auto:good,f_png,w_160,h_160&v=1519",
      "name": "雪原双子",
      "id": 162
    },
    {
      "image": "https://opgg-static.akamaized.net/meta/images/lol/15.19.1/champion/Camille.png?image=c_crop,h_103,w_103,x_9,y_9/q_auto:good,f_png,w_160,h_160&v=1519",
      "name": "青钢影",
      "id": 163
    },
    {
      "image": "https://opgg-static.akamaized.net/meta/images/lol/15.19.1/champion/Janna.png?image=c_crop,h_103,w_103,x_9,y_9/q_auto:good,f_png,w_160,h_160&v=1519",
      "name": "风暴之怒",
      "id": 164
    },
    {
      "image": "https://opgg-static.akamaized.net/meta/images/lol/15.19.1/champion/Thresh.png?image=c_crop,h_103,w_103,x_9,y_9/q_auto:good,f_png,w_160,h_160&v=1519",
      "name": "魂锁典狱长",
      "id": 165
    },
    {
      "image": "https://opgg-static.akamaized.net/meta/images/lol/15.19.1/champion/Yuumi.png?image=c_crop,h_103,w_103,x_9,y_9/q_auto:good,f_png,w_160,h_160&v=1519",
      "name": "魔法猫咪",
      "id": 166
    },
    {
      "image": "https://opgg-static.akamaized.net/meta/images/lol/15.19.1/champion/Cassiopeia.png?image=c_crop,h_103,w_103,x_9,y_9/q_auto:good,f_png,w_160,h_160&v=1519",
      "name": "魔蛇之拥",
      "id": 167
    },
    {
      "image": "https://opgg-static.akamaized.net/meta/images/lol/15.19.1/champion/Tristana.png?image=c_crop,h_103,w_103,x_9,y_9/q_auto:good,f_png,w_160,h_160&v=1519",
      "name": "麦林炮手",
      "id": 168
    },
    {
      "image": "https://opgg-static.akamaized.net/meta/images/lol/15.19.1/champion/Annie.png?image=c_crop,h_103,w_103,x_9,y_9/q_auto:good,f_png,w_160,h_160&v=1519",
      "name": "黑暗之女",
      "id": 169
    },
    {
      "image": "https://opgg-static.akamaized.net/meta/images/lol/15.19.1/champion/MonkeyKing.png?image=c_crop,h_103,w_103,x_9,y_9/q_auto:good,f_png,w_160,h_160&v=1519",
      "name": "齐天大圣",
      "id": 170
    },
    {
      "image": "https://opgg-static.akamaized.net/meta/images/lol/15.19.1/champion/Shyvana.png?image=c_crop,h_103,w_103,x_9,y_9/q_auto:good,f_png,w_160,h_160&v=1519",
      "name": "龙血武姬",
      "id": 171
    }
  ]
}